granim/__init__.py
granim/granim_plot.py
granim-0.1.1.data/scripts/granim-plot
granim-0.1.1.dist-info/LICENSE
granim-0.1.1.dist-info/METADATA
granim-0.1.1.dist-info/WHEEL
granim-0.1.1.dist-info/top_level.txt
granim-0.1.1.dist-info/zip-safe
granim-0.1.1.dist-info/RECORD
